Workbook
Name Diluted_Shares: 'ValSum (2)'!$E$35
Name Diluted_Shares: ValSum!$E$35

Sheet Public-Comps
B2: Comparable Companies - U.S.-Based Steel Manufacturer Companies with FY16 Projected Revenue Between $1 Billion and $20 Billion
B3: ($ USD in Millions Except Per Share Amounts in USD as Stated)
B5: Operating Statistics: | F5: Capitalization | U5: Projected | V5: Projected
D6: Share | E6: Diluted | F6: Equity | I6: Preferred | J6: Other & | K6: Enterprise | L6: Revenue | O6: EBITDA | R6: Net Income | U6: Revenue | V6: EBITDA | W6: EBITDA Margin
B7: Company Name | C7: Ticker | D7: Price | E7: Shares | F7: Value | G7: Cash | H7: Debt | I7: Stock | J7: NCI | K7: Value | L7: LTM | M7: =EOMONTH("12/31/2016",12) -> 43100 | N7: =EOMONTH(M7,12) -> 43465 | O7: =$L$7 -> LTM | P7: =+$M$7 -> 43100 | Q7: =+$N$7 -> 43465 | R7: =$L$7 -> LTM | S7: =+$M$7 -> 43100 | T7: =+$N$7 -> 43465 | U7: Growth | V7: Growth | W7: =$L$7 -> LTM | X7: =+$M$7 -> 43100 | Y7: =+$N$7 -> 43465
B8: United States Steel Corp. | C8: X | D8: 18.9 | E8: 165.61422 | F8: =+D8*E8 -> 3130.1088 | G8: -820 | H8: 3140 | I8: 0 | J8: 1 | K8: =+F8+G8+H8+I8+J8 -> 5451.1088 | L8: 10327 | M8: 10545.15 | N8: 11231.27 | O8: -128 | P8: 675 | Q8: 921.38 | R8: -1692 | S8: -74.89 | T8: 333.75 | U8: =IFERROR(+N8/M8-1,"N/A") -> 0.065064982 | V8: =IFERROR(+Q8/P8-1,"N/A") -> 0.36500741 | W8: =O8/L8 -> -0.012394694 | X8: =P8/M8 -> 0.064010469 | Y8: =Q8/N8 -> 0.082037027
B9: Nucor Corporation | C9: NUE | D9: 49.03 | E9: 318.35566 | F9: =+D9*E9 -> 15608.978 | G9: -2331.15 | H9: 4357.512 | I9: 0 | J9: 346.946 | K9: =+F9+G9+H9+I9+J9 -> 17982.286 | L9: 15643.6 | M9: 16684.82 | N9: 16937.09 | O9: 1972.9 | P9: 2291.4 | Q9: 2539.62 | R9: 469.6 | S9: 818.31 | T9: 1000.96 | U9: =IFERROR(+N9/M9-1,"N/A") -> 0.015119732 | V9: =IFERROR(+Q9/P9-1,"N/A") -> 0.10832679 | W9: =O9/L9 -> 0.12611547 | X9: =P9/M9 -> 0.13733442 | Y9: =Q9/N9 -> 0.14994429
B10: Commercial Metals Company | C10: CMC | D10: 15.5 | E10: 114.62859 | F10: =+D10*E10 -> 1776.7431 | G10: -483.855 | H10: 1079.95 | I10: 0 | J10: 0.16 | K10: =+F10+G10+H10+I10+J10 -> 2372.9981 | L10: 4813.4 | M10: 4683.9467 | N10: 4780.1033 | O10: 431.9 | P10: 367.43 | Q10: 423.11333 | R10: 129.4 | S10: 127.40667 | T10: 171.48667 | U10: =IFERROR(+N10/M10-1,"N/A") -> 0.020528984 | V10: =IFERROR(+Q10/P10-1,"N/A") -> 0.15154814 | W10: =O10/L10 -> 0.089728674 | X10: =P10/M10 -> 0.078444531 | Y10: =Q10/N10 -> 0.08851552
B11: AK Steel Holding Corporation | C11: AKS | D11: 4.35 | E11: 238.19619 | F11: =+D11*E11 -> 1036.1534 | G11: -56.2 | H11: 2078.1 | I11: 0 | J11: 379.6 | K11: =+F11+G11+H11+I11+J11 -> 3437.6534 | L11: 6263.6 | M11: 5991.83 | N11: 6108.22 | O11: 547.2 | P11: 469.23 | Q11: 580.9 | R11: -135 | S11: 57.29 | T11: 128.85 | U11: =IFERROR(+N11/M11-1,"N/A") -> 0.019424783 | V11: =IFERROR(+Q11/P11-1,"N/A") -> 0.23798564 | W11: =O11/L11 -> 0.087361901 | X11: =P11/M11 -> 0.078311634 | Y11: =Q11/N11 -> 0.095101355
B12: Worthington Industries, Inc. | C12: WOR | D12: 43.29 | E12: 63.115254 | F12: =+D12*E12 -> 2732.2593 | G12: -84.188 | H12: 583.96 | I12: 0 | J12: 126.48 | K12: =+F12+G12+H12+I12+J12 -> 3358.5113 | L12: 2819.7 | M12: 2891.3158 | N12: 2971.38 | O12: 239.9 | P12: 281.52667 | Q12: 324.07 | R12: 143.7 | S12: 177.3525 | T12: 220.33083 | U12: =IFERROR(+N12/M12-1,"N/A") -> 0.027691256 | V12: =IFERROR(+Q12/P12-1,"N/A") -> 0.15111653 | W12: =O12/L12 -> 0.085079973 | X12: =P12/M12 -> 0.097369739 | Y12: =Q12/N12 -> 0.1090638
B13: Reliance Steel & Aluminum Co. | C13: RS | D13: 72.51 | E13: 72.529836 | F13: =+D13*E13 -> 5259.1384 | G13: -116.5 | H13: 2169.4 | I13: 0 | J13: 28.6 | K13: =+F13+G13+H13+I13+J13 -> 7340.6384 | L13: 8679 | M13: 8890.36 | N13: 9303.56 | O13: 784.6 | P13: 850.74 | Q13: 928.7 | R13: 313.1 | S13: 390.23 | T13: 441.55 | U13: =IFERROR(+N13/M13-1,"N/A") -> 0.046477308 | V13: =IFERROR(+Q13/P13-1,"N/A") -> 0.091637868 | W13: =O13/L13 -> 0.09040212 | X13: =P13/M13 -> 0.095692413 | Y13: =Q13/N13 -> 0.099822004
B15: Maximum | D15: =MAX(D8:D13) -> 72.51 | F15: =MAX(F8:F13) -> 15608.978 | K15: =MAX(K8:K13) -> 17982.286 | L15: =MAX(L8:L13) -> 15643.6 | M15: =MAX(M8:M13) -> 16684.82 | N15: =MAX(N8:N13) -> 16937.09 | O15: =MAX(O8:O13) -> 1972.9 | P15: =MAX(P8:P13) -> 2291.4 | Q15: =MAX(Q8:Q13) -> 2539.62 | R15: =MAX(R8:R13) -> 469.6 | ... Y15: =MAX(Y8:Y13) -> 0.14994429
B16: 75th Percentile | D16: =QUARTILE(D8:D13,3) -> 47.595 | F16: =QUARTILE(F8:F13,3) -> 4726.881 | K16: =QUARTILE(K8:K13,3) -> 6868.256 | L16: =QUARTILE(L8:L13,3) -> 9915 | M16: =QUARTILE(M8:M13,3) -> 10131.452 | N16: =QUARTILE(N8:N13,3) -> 10749.343 | O16: =QUARTILE(O8:O13,3) -> 725.25 | P16: =QUARTILE(P8:P13,3) -> 806.805 | Q16: =QUARTILE(Q8:Q13,3) -> 926.87 | R16: =QUARTILE(R8:R13,3) -> 270.75 | ... Y16: =QUARTILE(Y8:Y13,3) -> 0.10675335
B17: Median | D17: =MEDIAN(D8:D13) -> 31.095 | F17: =MEDIAN(F8:F13) -> 2931.1841 | K17: =MEDIAN(K8:K13) -> 4444.3811 | L17: =MEDIAN(L8:L13) -> 7471.3 | M17: =MEDIAN(M8:M13) -> 7441.095 | N17: =MEDIAN(N8:N13) -> 7705.89 | O17: =MEDIAN(O8:O13) -> 489.55 | P17: =MEDIAN(P8:P13) -> 572.115 | Q17: =MEDIAN(Q8:Q13) -> 751.14 | R17: =MEDIAN(R8:R13) -> 136.55 | ... Y17: =MEDIAN(Y8:Y13) -> 0.097461679
B18: 25th Percentile | D18: =QUARTILE(D8:D13,1) -> 16.35 | F18: =QUARTILE(F8:F13,1) -> 2015.6222 | K18: =QUARTILE(K8:K13,1) -> 3378.2969 | L18: =QUARTILE(L8:L13,1) -> 5175.95 | M18: =QUARTILE(M8:M13,1) -> 5010.9175 | N18: =QUARTILE(N8:N13,1) -> 5112.1325 | O18: =QUARTILE(O8:O13,1) -> 287.9 | P18: =QUARTILE(P8:P13,1) -> 392.88 | Q18: =QUARTILE(Q8:Q13,1) -> 462.56 | R18: =QUARTILE(R8:R13,1) -> -68.9 | ... Y18: =QUARTILE(Y8:Y13,1) -> 0.090161979
B19: Minimum | D19: =MIN(D8:D13) -> 4.35 | F19: =MIN(F8:F13) -> 1036.1534 | K19: =MIN(K8:K13) -> 2372.9981 | L19: =MIN(L8:L13) -> 2819.7 | M19: =MIN(M8:M13) -> 2891.3158 | N19: =MIN(N8:N13) -> 2971.38 | O19: =MIN(O8:O13) -> -128 | P19: =MIN(P8:P13) -> 281.52667 | Q19: =MIN(Q8:Q13) -> 324.07 | R19: =MIN(R8:R13) -> -1692 | ... Y19: =MIN(Y8:Y13) -> 0.082037027
B21: Steel Dynamics Inc. | C21: STLD | D21: 24.97 | E21: =Diluted_Shares -> 242.017 | F21: =+D21*E21 -> 6043.1645 | G21: =-ValSum!E23-ValSum!E24-ValSum!E25-ValSum!E26 -> -1133.369 | H21: =-ValSum!E27 -> 2700 | I21: =-ValSum!E28 -> 0 | J21: =-ValSum!E29-ValSum!E30-ValSum!E31-ValSum!E32 -> -11.231 | K21: =+F21+G21+H21+I21+J21 -> 7598.5645 | L21: 7307.2 | M21: 7716.0164 | N21: 8406.1512 | O21: 862.8 | P21: 626.35222 | Q21: 730.23721 | R21: 12.1 | S21: 170.74786 | T21: 205.77268 | U21: =IFERROR(+N21/M21-1,"N/A") -> 0.089441861 | V21: =IFERROR(+Q21/P21-1,"N/A") -> 0.16585715 | W21: =O21/L21 -> 0.11807532 | X21: =P21/M21 -> 0.081175595 | Y21: =Q21/N21 -> 0.086869388
B23: Valuation Statistics: | F23: Capitalization | L23: Enterprise Value / | O23: Enterprise Value /
F24: Equity | K24: Enterprise | L24: Revenue | O24: EBITDA | R24: P / E Multiple
B25: Company Name | F25: Value | K25: Value | L25: =$L$7 -> LTM | M25: =+$M$7 -> 43100 | N25: =+$N$7 -> 43465 | O25: =$L$7 -> LTM | P25: =+$M$7 -> 43100 | Q25: =+$N$7 -> 43465 | R25: =$L$7 -> LTM | S25: =+$M$7 -> 43100 | T25: =+$N$7 -> 43465
B26: =+B8 -> United States Steel Corp. | C26: =+C8 -> X | F26: =+F8 -> 3130.1088 | K26: =+K8 -> 5451.1088 | L26: =IFERROR(IF(OR(+$K8/L8<0,+$K8/L8>=100),"NM",+$K8/L8),"N/A") -> 0.52785018 | M26: =IFERROR(IF(OR(+$K8/M8<0,+$K8/M8>=100),"NM",+$K8/M8),"N/A") -> 0.51693042 | N26: =IFERROR(IF(OR(+$K8/N8<0,+$K8/N8>=100),"NM",+$K8/N8),"N/A") -> 0.48535106 | O26: =IFERROR(IF(OR(+$K8/O8<0,+$K8/O8>=100),"NM",+$K8/O8),"N/A") -> NM | P26: =IFERROR(IF(OR(+$K8/P8<0,+$K8/P8>=100),"NM",+$K8/P8),"N/A") -> 8.0757168 | Q26: =IFERROR(IF(OR(+$K8/Q8<0,+$K8/Q8>=100),"NM",+$K8/Q8),"N/A") -> 5.9162439 | R26: =IFERROR(IF(OR(+$F8/R8<0,+$F8/R8>=100),"NM",+$F8/R8),"N/A") -> NM | S26: =IFERROR(IF(OR(+$F8/S8<0,+$F8/S8>=100),"NM",+$F8/S8),"N/A") -> NM | T26: =IFERROR(IF(OR(+$F8/T8<0,+$F8/T8>=100),"NM",+$F8/T8),"N/A") -> 9.3786032
B27: =+B9 -> Nucor Corporation | C27: =+C9 -> NUE | F27: =+F9 -> 15608.978 | K27: =+K9 -> 17982.286 | L27: =IFERROR(IF(OR(+$K9/L9<0,+$K9/L9>=100),"NM",+$K9/L9),"N/A") -> 1.149498 | M27: =IFERROR(IF(OR(+$K9/M9<0,+$K9/M9>=100),"NM",+$K9/M9),"N/A") -> 1.0777633 | N27: =IFERROR(IF(OR(+$K9/N9<0,+$K9/N9>=100),"NM",+$K9/N9),"N/A") -> 1.0617105 | O27: =IFERROR(IF(OR(+$K9/O9<0,+$K9/O9>=100),"NM",+$K9/O9),"N/A") -> 9.1146466 | P27: =IFERROR(IF(OR(+$K9/P9<0,+$K9/P9>=100),"NM",+$K9/P9),"N/A") -> 7.847729 | Q27: =IFERROR(IF(OR(+$K9/Q9<0,+$K9/Q9>=100),"NM",+$K9/Q9),"N/A") -> 7.0806996 | R27: =IFERROR(IF(OR(+$F9/R9<0,+$F9/R9>=100),"NM",+$F9/R9),"N/A") -> 33.23888 | S27: =IFERROR(IF(OR(+$F9/S9<0,+$F9/S9>=100),"NM",+$F9/S9),"N/A") -> 19.074652 | T27: =IFERROR(IF(OR(+$F9/T9<0,+$F9/T9>=100),"NM",+$F9/T9),"N/A") -> 15.594008
B28: =+B10 -> Commercial Metals Company | C28: =+C10 -> CMC | F28: =+F10 -> 1776.7431 | K28: =+K10 -> 2372.9981 | L28: =IFERROR(IF(OR(+$K10/L10<0,+$K10/L10>=100),"NM",+$K10/L10),"N/A") -> 0.49299832 | M28: =IFERROR(IF(OR(+$K10/M10<0,+$K10/M10>=100),"NM",+$K10/M10),"N/A") -> 0.50662364 | N28: =IFERROR(IF(OR(+$K10/N10<0,+$K10/N10>=100),"NM",+$K10/N10),"N/A") -> 0.49643239 | O28: =IFERROR(IF(OR(+$K10/O10<0,+$K10/O10>=100),"NM",+$K10/O10),"N/A") -> 5.494323 | P28: =IFERROR(IF(OR(+$K10/P10<0,+$K10/P10>=100),"NM",+$K10/P10),"N/A") -> 6.4583679 | Q28: =IFERROR(IF(OR(+$K10/Q10<0,+$K10/Q10>=100),"NM",+$K10/Q10),"N/A") -> 5.608422 | R28: =IFERROR(IF(OR(+$F10/R10<0,+$F10/R10>=100),"NM",+$F10/R10),"N/A") -> 13.730627 | S28: =IFERROR(IF(OR(+$F10/S10<0,+$F10/S10>=100),"NM",+$F10/S10),"N/A") -> 13.945449 | T28: =IFERROR(IF(OR(+$F10/T10<0,+$F10/T10>=100),"NM",+$F10/T10),"N/A") -> 10.360824
B29: =+B11 -> AK Steel Holding Corporation | C29: =+C11 -> AKS | F29: =+F11 -> 1036.1534 | K29: =+K11 -> 3437.6534 | L29: =IFERROR(IF(OR(+$K11/L11<0,+$K11/L11>=100),"NM",+$K11/L11),"N/A") -> 0.54883029 | M29: =IFERROR(IF(OR(+$K11/M11<0,+$K11/M11>=100),"NM",+$K11/M11),"N/A") -> 0.57372346 | N29: =IFERROR(IF(OR(+$K11/N11<0,+$K11/N11>=100),"NM",+$K11/N11),"N/A") -> 0.56279136 | O29: =IFERROR(IF(OR(+$K11/O11<0,+$K11/O11>=100),"NM",+$K11/O11),"N/A") -> 6.2822614 | P29: =IFERROR(IF(OR(+$K11/P11<0,+$K11/P11>=100),"NM",+$K11/P11),"N/A") -> 7.3261586 | Q29: =IFERROR(IF(OR(+$K11/Q11<0,+$K11/Q11>=100),"NM",+$K11/Q11),"N/A") -> 5.9178059 | R29: =IFERROR(IF(OR(+$F11/R11<0,+$F11/R11>=100),"NM",+$F11/R11),"N/A") -> NM | S29: =IFERROR(IF(OR(+$F11/S11<0,+$F11/S11>=100),"NM",+$F11/S11),"N/A") -> 18.086113 | T29: =IFERROR(IF(OR(+$F11/T11<0,+$F11/T11>=100),"NM",+$F11/T11),"N/A") -> 8.0415477
B30: =+B12 -> Worthington Industries, Inc. | C30: =+C12 -> WOR | F30: =+F12 -> 2732.2593 | K30: =+K12 -> 3358.5113 | L30: =IFERROR(IF(OR(+$K12/L12<0,+$K12/L12>=100),"NM",+$K12/L12),"N/A") -> 1.1910882 | M30: =IFERROR(IF(OR(+$K12/M12<0,+$K12/M12>=100),"NM",+$K12/M12),"N/A") -> 1.1615858 | N30: =IFERROR(IF(OR(+$K12/N12<0,+$K12/N12>=100),"NM",+$K12/N12),"N/A") -> 1.1302867 | O30: =IFERROR(IF(OR(+$K12/O12<0,+$K12/O12>=100),"NM",+$K12/O12),"N/A") -> 13.99963 | P30: =IFERROR(IF(OR(+$K12/P12<0,+$K12/P12>=100),"NM",+$K12/P12),"N/A") -> 11.929638 | Q30: =IFERROR(IF(OR(+$K12/Q12<0,+$K12/Q12>=100),"NM",+$K12/Q12),"N/A") -> 10.363537 | R30: =IFERROR(IF(OR(+$F12/R12<0,+$F12/R12>=100),"NM",+$F12/R12),"N/A") -> 19.013635 | S30: =IFERROR(IF(OR(+$F12/S12<0,+$F12/S12>=100),"NM",+$F12/S12),"N/A") -> 15.405812 | T30: =IFERROR(IF(OR(+$F12/T12<0,+$F12/T12>=100),"NM",+$F12/T12),"N/A") -> 12.400713
B31: =+B13 -> Reliance Steel & Aluminum Co. | C31: =+C13 -> RS | F31: =+F13 -> 5259.1384 | K31: =+K13 -> 7340.6384 | L31: =IFERROR(IF(OR(+$K13/L13<0,+$K13/L13>=100),"NM",+$K13/L13),"N/A") -> 0.84579311 | M31: =IFERROR(IF(OR(+$K13/M13<0,+$K13/M13>=100),"NM",+$K13/M13),"N/A") -> 0.82568517 | N31: =IFERROR(IF(OR(+$K13/N13<0,+$K13/N13>=100),"NM",+$K13/N13),"N/A") -> 0.78901393 | O31: =IFERROR(IF(OR(+$K13/O13<0,+$K13/O13>=100),"NM",+$K13/O13),"N/A") -> 9.3558991 | P31: =IFERROR(IF(OR(+$K13/P13<0,+$K13/P13>=100),"NM",+$K13/P13),"N/A") -> 8.6285333 | Q31: =IFERROR(IF(OR(+$K13/Q13<0,+$K13/Q13>=100),"NM",+$K13/Q13),"N/A") -> 7.9042085 | R31: =IFERROR(IF(OR(+$F13/R13<0,+$F13/R13>=100),"NM",+$F13/R13),"N/A") -> 16.796993 | S31: =IFERROR(IF(OR(+$F13/S13<0,+$F13/S13>=100),"NM",+$F13/S13),"N/A") -> 13.477022 | T31: =IFERROR(IF(OR(+$F13/T13<0,+$F13/T13>=100),"NM",+$F13/T13),"N/A") -> 11.910629
B33: Maximum | F33: =MAX(F26:F31) -> 15608.978 | K33: =MAX(K26:K31) -> 17982.286 | L33: =MAX(L26:L31) -> 1.1910882 | M33: =MAX(M26:M31) -> 1.1615858 | N33: =MAX(N26:N31) -> 1.1302867 | O33: =MAX(O26:O31) -> 13.99963 | P33: =MAX(P26:P31) -> 11.929638 | Q33: =MAX(Q26:Q31) -> 10.363537 | R33: =MAX(R26:R31) -> 33.23888 | ... T33: =MAX(T26:T31) -> 15.594008
B34: 75th Percentile | F34: =QUARTILE(F26:F31,3) -> 4726.881 | K34: =QUARTILE(K26:K31,3) -> 6868.256 | L34: =QUARTILE(L26:L31,3) -> 1.0735717 | M34: =QUARTILE(M26:M31,3) -> 1.0147437 | N34: =QUARTILE(N26:N31,3) -> 0.99353636 | O34: =QUARTILE(O26:O31,3) -> 9.3558991 | P34: =QUARTILE(P26:P31,3) -> 8.4903292 | Q34: =QUARTILE(Q26:Q31,3) -> 7.6983312 | R34: =QUARTILE(R26:R31,3) -> 22.569946 | ... T34: =QUARTILE(T26:T31,3) -> 12.278192
B35: Median | F35: =MEDIAN(F26:F31) -> 2931.1841 | K35: =MEDIAN(K26:K31) -> 4444.3811 | L35: =MEDIAN(L26:L31) -> 0.6973117 | M35: =MEDIAN(M26:M31) -> 0.69970431 | N35: =MEDIAN(N26:N31) -> 0.67590264 | O35: =MEDIAN(O26:O31) -> 9.1146466 | P35: =MEDIAN(P26:P31) -> 7.9617229 | Q35: =MEDIAN(Q26:Q31) -> 6.4992527 | R35: =MEDIAN(R26:R31) -> 17.905314 | ... T35: =MEDIAN(T26:T31) -> 11.135727
B36: 25th Percentile | F36: =QUARTILE(F26:F31,1) -> 2015.6222 | K36: =QUARTILE(K26:K31,1) -> 3378.2969 | L36: =QUARTILE(L26:L31,1) -> 0.53309521 | M36: =QUARTILE(M26:M31,1) -> 0.53112868 | N36: =QUARTILE(N26:N31,1) -> 0.51302213 | O36: =QUARTILE(O26:O31,1) -> 6.2822614 | P36: =QUARTILE(P26:P31,1) -> 7.4565512 | Q36: =QUARTILE(Q26:Q31,1) -> 5.9166344 | R36: =QUARTILE(R26:R31,1) -> 16.030401 | ... T36: =QUARTILE(T26:T31,1) -> 9.6241583
B37: Minimum | F37: =MIN(F26:F31) -> 1036.1534 | K37: =MIN(K26:K31) -> 2372.9981 | L37: =MIN(L26:L31) -> 0.49299832 | M37: =MIN(M26:M31) -> 0.50662364 | N37: =MIN(N26:N31) -> 0.48535106 | O37: =MIN(O26:O31) -> 5.494323 | P37: =MIN(P26:P31) -> 6.4583679 | Q37: =MIN(Q26:Q31) -> 5.608422 | R37: =MIN(R26:R31) -> 13.730627 | ... T37: =MIN(T26:T31) -> 8.0415477
B39: =B21 -> Steel Dynamics Inc. | C39: =C21 -> STLD | F39: =+F21 -> 6043.1645 | K39: =+K21 -> 7598.5645 | L39: =IFERROR(IF(OR(+$K21/L21<0,+$K21/L21>=100),"NM",+$K21/L21),"N/A") -> 1.0398736 | M39: =IFERROR(IF(OR(+$K21/M21<0,+$K21/M21>=100),"NM",+$K21/M21),"N/A") -> 0.98477817 | N39: =IFERROR(IF(OR(+$K21/N21<0,+$K21/N21>=100),"NM",+$K21/N21),"N/A") -> 0.90392907 | O39: =IFERROR(IF(OR(+$K21/O21<0,+$K21/O21>=100),"NM",+$K21/O21),"N/A") -> 8.8068666 | P39: =IFERROR(IF(OR(+$K21/P21<0,+$K21/P21>=100),"NM",+$K21/P21),"N/A") -> 12.131456 | Q39: =IFERROR(IF(OR(+$K21/Q21<0,+$K21/Q21>=100),"NM",+$K21/Q21),"N/A") -> 10.405611 | R39: =IFERROR(IF(OR(+$F21/R21<0,+$F21/R21>=100),"NM",+$F21/R21),"N/A") -> NM | S39: =IFERROR(IF(OR(+$F21/S21<0,+$F21/S21>=100),"NM",+$F21/S21),"N/A") -> 35.392328 | T39: =IFERROR(IF(OR(+$F21/T21<0,+$F21/T21>=100),"NM",+$F21/T21),"N/A") -> 29.368157

Sheet Public-Comps (2)
B2: Comparable Companies - U.S.-Based Steel Manufacturer Companies with FY16 Projected Revenue Between $1 Billion and $20 Billion
B3: ($ USD in Millions Except Per Share Amounts in USD as Stated)
B5: Operating Statistics: | F5: Capitalization | U5: Projected | V5: Projected
D6: Share | E6: Diluted | F6: Equity | I6: Preferred | J6: Other & | K6: Enterprise | L6: Revenue | O6: EBITDA | R6: Net Income | U6: Revenue | V6: EBITDA | W6: EBITDA Margin
B7: Company Name | C7: Ticker | D7: Price | E7: Shares | F7: Value | G7: Cash | H7: Debt | I7: Stock | J7: NCI | K7: Value | L7: LTM | M7: =EOMONTH("12/31/2016",12) -> #VALUE! | N7: =EOMONTH(M7,12) -> #VALUE! | O7: =$L$7 -> LTM | P7: =+$M$7 -> #VALUE! | Q7: =+$N$7 -> #VALUE! | R7: =$L$7 -> LTM | S7: =+$M$7 -> #VALUE! | T7: =+$N$7 -> #VALUE! | U7: Growth | V7: Growth | W7: =$L$7 -> LTM | X7: =+$M$7 -> #VALUE! | Y7: =+$N$7 -> #VALUE!
B8: United States Steel Corp. | C8: X | D8: 54.84
B9: Nucor Corporation | C9: NUE | D9: 250.49 | E9: 231 | F9: =D9*E9 -> 57863.19 | G9: 2260
B10: Commercial Metals Company | C10: CMC | D10: 73.57 | E10: 114.08675 | F10: =D10*E10 -> 8393.3622 | G10: =1043252*1000/1000000 -> 1043.252
B11: Ryerson Holding Corp | C11: ZEUS | D11: 24.6 | E11: =32116*1000/1000000 -> 32.116 | F11: =D11*E11 -> 790.0536 | G11: 26.9
B12: Worthington Industries, Inc. | C12: WOR | D12: 57.49 | E12: =50131*1000/1000000 -> 50.131 | F12: =D12*E12 -> 2882.0312 | G12: =250075*1000/1000000 -> 250.075
B13: Reliance Steel & Aluminum Co. | C13: RS | D13: 394.29 | E13: =52375*1000/1000000 -> 52.375 | F13: =D13*E13 -> 20650.939 | G13: 216.6
B15: Maximum
B16: 75th Percentile
B17: Median
B18: 25th Percentile
B19: Minimum
B21: Steel Dynamics Inc. | C21: STLD
B23: Valuation Statistics: | F23: Capitalization | L23: Enterprise Value / | O23: Enterprise Value /
F24: Equity | K24: Enterprise | L24: Revenue | O24: EBITDA | R24: P / E Multiple
B25: Company Name | F25: Value | K25: Value | L25: =$L$7 -> LTM | M25: =+$M$7 -> #VALUE! | N25: =+$N$7 -> #VALUE! | O25: =$L$7 -> LTM | P25: =+$M$7 -> #VALUE! | Q25: =+$N$7 -> #VALUE! | R25: =$L$7 -> LTM | S25: =+$M$7 -> #VALUE! | T25: =+$N$7 -> #VALUE!
B26: =+B8 -> United States Steel Corp. | C26: =+C8 -> X
B27: =+B9 -> Nucor Corporation | C27: =+C9 -> NUE
B28: =+B10 -> Commercial Metals Company | C28: =+C10 -> CMC
B29: =+B11 -> Ryerson Holding Corp | C29: =+C11 -> ZEUS
B30: =+B12 -> Worthington Industries, Inc. | C30: =+C12 -> WOR
B31: =+B13 -> Reliance Steel & Aluminum Co. | C31: =+C13 -> RS
B33: Maximum
B34: 75th Percentile
B35: Median
B36: 25th Percentile
B37: Minimum
B39: =B21 -> Steel Dynamics Inc. | C39: =C21 -> STLD

Sheet ValSum
B2: Valuation Summary - Steel Dynamics Inc.
B3: ($ USD in Millions Except Per Share Amounts in USD as Stated)
B5: Valuation Summary - Steel Dynamics Inc. | C5: Steel Dynamics Inc. - Range of Valuation Multiples / Premiums | I5: Steel Dynamics Inc. - Implied Per Share Value Range
D7: 75th | F7: 25th | H7: Applicable | J7: 25th | L7: 75th
C8: Maximum | D8: Percentile | E8: Median | F8: Percentile | G8: Minimum | H8: Company | I8: Minimum | J8: Percentile | K8: Median | L8: Percentile | M8: Maximum
B9: Methodology Name | C9: Multiple | D9: Multiple | E9: Multiple | F9: Multiple | G9: Multiple | H9: Figure | I9: Multiple | J9: Multiple | K9: Multiple | L9: Multiple | M9: Multiple
B11: Public Company Comparables:
B12: LTM EV / Revenue: | C12: {=TRANSPOSE('Public-Comps'!L33:T37)} -> 1.1910882 | D12: 1.0735717 | E12: 0.6973117 | F12: 0.53309521 | G12: 0.49299832 | H12: {=TRANSPOSE('Public-Comps'!L21:T21)} -> 7307.2 | I12: =(+I24+SUM($E$23:$E$32))/Diluted_Shares -> 8.4582377 | J12: =(+J24+SUM($E$23:$E$32))/Diluted_Shares -> 9.6688799 | K12: =(+K24+SUM($E$23:$E$32))/Diluted_Shares -> 14.627055 | L12: =(+L24+SUM($E$23:$E$32))/Diluted_Shares -> 25.987445 | M12: =(+M24+SUM($E$23:$E$32))/Diluted_Shares -> 29.535609
B13: ="FY "&TEXT(EOMONTH("12/31/2016",12),"YY")&" EV / Revenue:" -> FY 17 EV / Revenue: | C13: 1.1615858 | D13: 1.0147437 | E13: 0.69970431 | F13: 0.53112868 | G13: 0.50662364 | H13: 7716.0164 | I13: =(+I25+SUM($E$23:$E$32))/Diluted_Shares -> 9.7254173 | J13: =(+J25+SUM($E$23:$E$32))/Diluted_Shares -> 10.50669 | K13: =(+K25+SUM($E$23:$E$32))/Diluted_Shares -> 15.88124 | L13: =(+L25+SUM($E$23:$E$32))/Diluted_Shares -> 25.925366 | M13: =(+M25+SUM($E$23:$E$32))/Diluted_Shares -> 30.607002
B14: ="FY "&TEXT(EOMONTH("12/31/2016",24),"YY")&" EV / Revenue:" -> FY 18 EV / Revenue: | C14: 1.1302867 | D14: 0.99353636 | E14: 0.67590264 | F14: 0.51302213 | G14: 0.48535106 | H14: 8406.1512 | I14: =(+I26+SUM($E$23:$E$32))/Diluted_Shares -> 10.431228 | J14: =(+J26+SUM($E$23:$E$32))/Diluted_Shares -> 11.392347 | K14: =(+K26+SUM($E$23:$E$32))/Diluted_Shares -> 17.049793 | L14: =(+L26+SUM($E$23:$E$32))/Diluted_Shares -> 28.082394 | M14: =(+M26+SUM($E$23:$E$32))/Diluted_Shares -> 32.832244
B15: LTM EV / EBITDA: | C15: 13.99963 | D15: 9.3558991 | E15: 9.1146466 | F15: 6.2822614 | G15: 5.494323 | H15: 862.8 | I15: =(+I27+SUM($E$23:$E$32))/Diluted_Shares -> 13.160654 | J15: =(+J27+SUM($E$23:$E$32))/Diluted_Shares -> 15.969684 | K15: =(+K27+SUM($E$23:$E$32))/Diluted_Shares -> 26.067248 | L15: =(+L27+SUM($E$23:$E$32))/Diluted_Shares -> 26.927322 | M15: =(+M27+SUM($E$23:$E$32))/Diluted_Shares -> 43.482405
B16: ="FY "&TEXT(EOMONTH("12/31/2016",12),"YY")&" EV / EBITDA:" -> FY 17 EV / EBITDA: | C16: 11.929638 | D16: 8.4903292 | E16: 7.9617229 | F16: 7.4565512 | G16: 6.4583679 | H16: 626.35222 | I16: =(+I28+SUM($E$23:$E$32))/Diluted_Shares -> 10.287761 | J16: =(+J28+SUM($E$23:$E$32))/Diluted_Shares -> 12.87111 | K16: =(+K28+SUM($E$23:$E$32))/Diluted_Shares -> 14.17852 | L16: =(+L28+SUM($E$23:$E$32))/Diluted_Shares -> 15.546579 | M16: =(+M28+SUM($E$23:$E$32))/Diluted_Shares -> 24.447686
B17: ="FY "&TEXT(EOMONTH("12/31/2016",24),"YY")&" EV / EBITDA:" -> FY 18 EV / EBITDA: | C17: 10.363537 | D17: 7.6983312 | E17: 6.4992527 | F17: 5.9166344 | G17: 5.608422 | H17: 730.23721 | I17: =(+I29+SUM($E$23:$E$32))/Diluted_Shares -> 10.495455 | J17: =(+J29+SUM($E$23:$E$32))/Diluted_Shares -> 11.425423 | K17: =(+K29+SUM($E$23:$E$32))/Diluted_Shares -> 13.183356 | L17: =(+L29+SUM($E$23:$E$32))/Diluted_Shares -> 16.801332 | M17: =(+M29+SUM($E$23:$E$32))/Diluted_Shares -> 24.843049
B18: LTM P / E: | C18: 33.23888 | D18: 22.569946 | E18: 17.905314 | F18: 16.030401 | G18: 13.730627 | H18: 12.1 | I18: =+I30/Diluted_Shares -> 0.68648312 | J18: =+J30/Diluted_Shares -> 0.80146376 | K18: =+K30/Diluted_Shares -> 0.89520281 | L18: =+L30/Diluted_Shares -> 1.128418 | M18: =+M30/Diluted_Shares -> 1.6618273
B19: ="FY "&TEXT(EOMONTH("12/31/2016",12),"YY")&" P / E:" -> FY 17 P / E: | C19: 19.074652 | D19: 18.086113 | E19: 15.405812 | F19: 13.945449 | G19: 13.477022 | H19: 170.74786 | I19: =+I31/Diluted_Shares -> 9.5083104 | J19: =+J31/Diluted_Shares -> 9.8387946 | K19: =+K31/Diluted_Shares -> 10.869111 | L19: =+L31/Diluted_Shares -> 12.760117 | M19: =+M31/Diluted_Shares -> 13.457551
B20: ="FY "&TEXT(EOMONTH("12/31/2016",24),"YY")&" P / E:" -> FY 18 P / E: | C20: 15.594008 | D20: 12.278192 | E20: 11.135727 | F20: 9.6241583 | G20: 8.0415477 | H20: 205.77268 | I20: =+I32/Diluted_Shares -> 6.8372505 | J20: =+J32/Diluted_Shares -> 8.1828503 | K20: =+K32/Diluted_Shares -> 9.468047 | L20: =+L32/Diluted_Shares -> 10.439417 | M20: =+M32/Diluted_Shares -> 13.258659
B22: Implied Enterprise Value: | E22: =+I24 -> 3602.4373 | G22: Implied Enterprise Value or Equity Value at a Range of Multiples:
B23: (+) Cash & Cash-Equivalents: | E23: 1072.221
B24: (+) Equity Investments: | E24: 0 | G24: Enterprise Value --> | I24: =+$H12*G12 -> 3602.4373 | J24: =+$H12*F12 -> 3895.4333 | K24: =+$H12*E12 -> 5095.3961 | L24: =+$H12*D12 -> 7844.8035 | M24: =+$H12*C12 -> 8703.5196
B25: (+) Other Non-Core Assets, Net: | E25: 0 | G25: Enterprise Value --> | I25: =+$H13*G13 -> 3909.1163 | J25: =+$H13*F13 -> 4098.1976 | K25: =+$H13*E13 -> 5398.9299 | L25: =+$H13*D13 -> 7829.7794 | M25: =+$H13*C13 -> 8962.8149
B26: (+) Net Operating Losses: | E26: 61.148 | G26: Enterprise Value --> | I26: =+$H14*G14 -> 4079.9344 | J26: =+$H14*F14 -> 4312.5416 | K26: =+$H14*E14 -> 5681.7398 | L26: =+$H14*D14 -> 8351.8169 | M26: =+$H14*C14 -> 9501.3611
B27: (-) Total Debt: | E27: -2700 | G27: Enterprise Value --> | I27: =+$H15*G15 -> 4740.5019 | J27: =+$H15*F15 -> 5420.3351 | K27: =+$H15*E15 -> 7864.1171 | L27: =+$H15*D15 -> 8072.2697 | M27: =+$H15*C15 -> 12078.881
B28: (-) Preferred Stock: | E28: 0 | G28: Enterprise Value --> | I28: =+$H16*G16 -> 4045.2131 | J28: =+$H16*F16 -> 4670.4274 | K28: =+$H16*E16 -> 4986.8428 | L28: =+$H16*D16 -> 5317.9365 | M28: =+$H16*C16 -> 7472.1555
B29: (-) Noncontrolling Interests: | E29: 11.231 | G29: Enterprise Value --> | I29: =+$H17*G17 -> 4095.4784 | J29: =+$H17*F17 -> 4320.5466 | K29: =+$H17*E17 -> 4745.9962 | L29: =+$H17*D17 -> 5621.608 | M29: =+$H17*C17 -> 7567.8402
B30: (-) Unfunded Pension Obligations: | E30: 0 | G30: Equity Value --> | I30: =+$H18*G18 -> 166.14058 | J30: =+$H18*F18 -> 193.96785 | K30: =+$H18*E18 -> 216.6543 | L30: =+$H18*D18 -> 273.09635 | M30: =+$H18*C18 -> 402.19045
B31: (-) Capital Leases: | E31: 0 | G31: Equity Value --> | I31: =+$H19*G19 -> 2301.1728 | J31: =+$H19*F19 -> 2381.1556 | K31: =+$H19*E19 -> 2630.5096 | L31: =+$H19*D19 -> 3088.1652 | M31: =+$H19*C19 -> 3256.956
B32: (-) Restructuring & Other Liabilities: | E32: 0 | G32: Equity Value --> | I32: =+$H20*G20 -> 1654.7309 | J32: =+$H20*F20 -> 1980.3889 | K32: =+$H20*E20 -> 2291.4283 | L32: =+$H20*D20 -> 2526.5165 | M32: =+$H20*C20 -> 3208.8209
B33: Implied Equity Value: | E33: =SUM(E22:E32) -> 2047.0373
B35: Diluted Shares Outstanding: | E35: 242.017
B37: Implied Share Price from DCF: | E37: =+E33/E35 -> 8.4582377
B38: Premium / (Discount) to Current: | E38: =+E37/'Public-Comps'!D21-1 -> -0.66126401

Sheet ValSum (2)
B2: Valuation Summary - Steel Dynamics Inc.
B3: ($ USD in Millions Except Per Share Amounts in USD as Stated)
B5: Valuation Summary - Steel Dynamics Inc. | C5: Steel Dynamics Inc. - Range of Valuation Multiples / Premiums | I5: Steel Dynamics Inc. - Implied Per Share Value Range
D7: 75th | F7: 25th | H7: Applicable | J7: 25th | L7: 75th
C8: Maximum | D8: Percentile | E8: Median | F8: Percentile | G8: Minimum | H8: Company | I8: Minimum | J8: Percentile | K8: Median | L8: Percentile | M8: Maximum
B9: Methodology Name | C9: Multiple | D9: Multiple | E9: Multiple | F9: Multiple | G9: Multiple | H9: Figure | I9: Multiple | J9: Multiple | K9: Multiple | L9: Multiple | M9: Multiple
B11: Public Company Comparables:
B12: LTM EV / Revenue:
B13: FY 17 EV / Revenue:
B14: FY 18 EV / Revenue:
B15: LTM EV / EBITDA:
B16: FY 17 EV / EBITDA:
B17: FY 18 EV / EBITDA:
B18: LTM P / E:
B19: FY 17 P / E:
B20: FY 18 P / E:
B22: Implied Enterprise Value: | E22: =+I24 -> 0 | G22: Implied Enterprise Value or Equity Value at a Range of Multiples:
B23: (+) Cash & Cash-Equivalents:
B24: (+) Equity Investments: | G24: Enterprise Value -->
B25: (+) Other Non-Core Assets, Net: | G25: Enterprise Value -->
B26: (+) Net Operating Losses: | G26: Enterprise Value -->
B27: (-) Total Debt: | G27: Enterprise Value -->
B28: (-) Preferred Stock: | G28: Enterprise Value -->
B29: (-) Noncontrolling Interests: | G29: Enterprise Value -->
B30: (-) Unfunded Pension Obligations: | G30: Equity Value -->
B31: (-) Capital Leases: | G31: Equity Value -->
B32: (-) Restructuring & Other Liabilities: | G32: Equity Value -->
B33: Implied Equity Value:
B35: Diluted Shares Outstanding:
B37: Implied Share Price from DCF:
B38: Premium / (Discount) to Current:
